SAES/.gitignore
SAES/__init__.py
SAES/__main__.py
SAES/logger.py
SAES/html/__init__.py
SAES/html/html_generator.py
SAES/html/notebooks/bayesian_posterior.ipynb
SAES/html/notebooks/multiobjective_fronts2D.ipynb
SAES/html/notebooks/multiobjective_fronts3D.ipynb
SAES/html/notebooks/multiobjective_frontsND.ipynb
SAES/html/notebooks/multiobjective_optimization.ipynb
SAES/latex_generation/__init__.py
SAES/latex_generation/stats_table.py
SAES/multiobjective/__init__.py
SAES/multiobjective/pareto_front.py
SAES/plots/__init__.py
SAES/plots/boxplot.py
SAES/plots/cdplot.py
SAES/plots/histoplot.py
SAES/plots/pplot.py
SAES/plots/violin.py
SAES/statistical_tests/__init__.py
SAES/statistical_tests/apv_procedures.py
SAES/statistical_tests/bayesian.py
SAES/statistical_tests/non_parametrical.py
SAES/statistical_tests/parametrical.py
SAES/utils/__init__.py
SAES/utils/dataframe_processor.py
saes-1.4.0.dist-info/METADATA
saes-1.4.0.dist-info/WHEEL
saes-1.4.0.dist-info/licenses/LICENSE
saes-1.4.0.dist-info/RECORD
