Metadata-Version: 2.4
Name: SAES
Version: 1.4.0
Summary: Python library designed to analyze and compare the performance of different algorithms across multiple problems using non-parametric statistical tests
Author-email: "Antonio J. Nebro" <ajnebro@uma.es>, Emilio Rodrigo Carreira Villalta <emiliorodrigo.ecr@gmail.com>
Maintainer-email: "Antonio J. Nebro" <ajnebro@uma.es>, Emilio Rodrigo Carreira Villalta <emiliorodrigo.ecr@gmail.com>
License-File: LICENSE
Classifier: Development Status :: 5 - Production/Stable
Classifier: Intended Audience :: Science/Research
Classifier: License :: OSI Approved :: GNU General Public License v3 (GPLv3)
Classifier: Programming Language :: Python :: 3.10
Classifier: Topic :: Scientific/Engineering :: Artificial Intelligence
Requires-Python: >=3.10
Requires-Dist: jinja2==3.1.6
Requires-Dist: matplotlib==3.9.2
Requires-Dist: numpy<2
Requires-Dist: pandas>=1.3.0
Requires-Dist: papermill==2.6.0
Requires-Dist: python-dotenv==1.0.1
Requires-Dist: scikit-posthocs==0.10.0
Requires-Dist: scipy>=1.7.0
Requires-Dist: seaborn>=0.11.0
Provides-Extra: dev
Requires-Dist: black>=22.0.0; extra == 'dev'
Requires-Dist: coverage==7.6.8; extra == 'dev'
Requires-Dist: flake8>=4.0.0; extra == 'dev'
Requires-Dist: isort>=5.10.0; extra == 'dev'
Requires-Dist: mypy>=0.950; extra == 'dev'
Requires-Dist: pre-commit>=3.0.0; extra == 'dev'
Requires-Dist: pytest-cov>=3.0.0; extra == 'dev'
Requires-Dist: pytest>=7.0.0; extra == 'dev'
Requires-Dist: sphinx-rtd-theme==3.0.2; extra == 'dev'
Requires-Dist: sphinx==8.1.3; extra == 'dev'
Provides-Extra: docs
Requires-Dist: sphinx-rtd-theme==3.0.2; extra == 'docs'
Requires-Dist: sphinx==8.1.3; extra == 'docs'
Provides-Extra: html
Requires-Dist: ipykernel<=6.29.5; extra == 'html'
Requires-Dist: ipython<=8.30.0; extra == 'html'
Requires-Dist: nbconvert==7.16.6; extra == 'html'
Requires-Dist: papermill==2.6.0; extra == 'html'
Provides-Extra: test
Requires-Dist: coverage==7.6.8; extra == 'test'
Requires-Dist: pillow>=9.0.0; extra == 'test'
Requires-Dist: pytest-cov>=3.0.0; extra == 'test'
Requires-Dist: pytest>=7.0.0; extra == 'test'
